README
setup.py
bebop/__init__.py
bebop/config.py
bebop/connection.py
bebop/data_import.py
bebop/exception.py
bebop/index.py
bebop/interface.py
bebop/model.py
bebop/query.py
bebop/schema.py
bebop/util.py
bebop.egg-info/PKG-INFO
bebop.egg-info/SOURCES.txt
bebop.egg-info/dependency_links.txt
bebop.egg-info/requires.txt
bebop.egg-info/top_level.txt