Metadata-Version: 1.0
Name: bebop
Version: 0.0.6
Summary: Solr object mapping and schema generation without all the XML
Home-page: http://www.github.com/thatdatabaseguy/bebop
Author: Al Barrentine
Author-email: UNKNOWN
License: UNKNOWN
Platform: UNKNOWN
